check_talend_job/__init__.py
check_talend_job/check_talend_job.py
check_talend_job/config.py
check_talend_job/tests/test_check_talend_job.py
check_talend_job-0.2.dev0.dist-info/DESCRIPTION.rst
check_talend_job-0.2.dev0.dist-info/METADATA
check_talend_job-0.2.dev0.dist-info/RECORD
check_talend_job-0.2.dev0.dist-info/WHEEL
check_talend_job-0.2.dev0.dist-info/entry_points.txt
check_talend_job-0.2.dev0.dist-info/metadata.json
check_talend_job-0.2.dev0.dist-info/top_level.txt
