Metadata-Version: 2.0
Name: check-talend-job
Version: 0.2.dev0
Summary: A nagios-like plugin to check if talend jobs executed successfully
Home-page: https://github.com/paulla/check_talend_job
Author: Elio Maisonneuve
Author-email: maisonneuv@eisti.eu
License: BSD
Keywords: nagios
Platform: any
Classifier: Programming Language :: Python
Classifier: License :: OSI Approved :: BSD License
Requires-Dist: setuptools
